[
    {
        "scope": "https://api.opensuse.org:443",
        "method": "GET",
        "path": "/source/Virtualization:vagrant/vagrant-scp/_history",
        "body": "",
        "status": 200,
        "response": "<revisionlist>\n  <revision rev=\"1\" vrev=\"1\">\n    <srcmd5>5bc0dc1d511915859525852bc11eee1d</srcmd5>\n    <version>0.5.7</version>\n    <time>1559805477</time>\n    <user>ojkastl_buildservice</user>\n    <comment>first version, based on spec from vagrant-vbguest</comment>\n  </revision>\n  <revision rev=\"2\" vrev=\"2\">\n    <srcmd5>eb31bb09da66845da76334c0554d062f</srcmd5>\n    <version>0.5.7</version>\n    <time>1560109374</time>\n    <user>ojkastl_buildservice</user>\n    <comment>Install README.md &amp; LICENSE.txt</comment>\n    <requestid>708417</requestid>\n  </revision>\n  <revision rev=\"3\" vrev=\"3\">\n    <srcmd5>7303deb8640d5adce5b8f09c9638fbaf</srcmd5>\n    <version>0.5.7</version>\n    <time>1566562599</time>\n    <user>dancermak</user>\n    <comment>add runtime dependencies as BuildRequires, to easier notice missing dependencies; add patches to use newer versions of bundler and net-scp</comment>\n    <requestid>712282</requestid>\n  </revision>\n  <revision rev=\"4\" vrev=\"4\">\n    <srcmd5>3e0e3566753dca94980d3acd23b82efd</srcmd5>\n    <version>0.5.7</version>\n    <time>1585133120</time>\n    <user>dirkmueller</user>\n    <comment>Bump patched dependency on bundler to 2.1</comment>\n    <requestid>788130</requestid>\n  </revision>\n</revisionlist>\n",
        "rawHeaders": [
            "Date",
            "Fri, 29 May 2020 10:22:04 GMT",
            "Server",
            "Apache/2.4.33 (Linux/SUSE)",
            "Strict-Transport-Security",
            "max-age=31536000",
            "cache-control",
            "private, no-transform",
            "referrer-policy",
            "strict-origin-when-cross-origin",
            "x-permitted-cross-domain-policies",
            "none",
            "x-xss-protection",
            "1; mode=block",
            "x-opensuse-runtimes",
            "{\"view\":null,\"db\":12.704955413937569,\"backend\":0}",
            "x-request-id",
            "0b2d8d65-8d37-4892-926a-88e5e47064e7",
            "x-opensuse-apiversion",
            "2.11~alpha.20200525T144748.3dca262e02",
            "x-download-options",
            "noopen",
            "x-runtime",
            "0.037433",
            "x-frame-options",
            "SAMEORIGIN",
            "x-content-type-options",
            "nosniff",
            "x-powered-by",
            "Phusion Passenger 6.0.4",
            "content-type",
            "text/xml",
            "cache-control",
            "no-cache",
            "content-length",
            "1244",
            "Connection",
            "close"
        ],
        "responseIsBinary": false
    },
    {
        "scope": "https://api.opensuse.org:443",
        "method": "GET",
        "path": "/source/Virtualization:vagrant/vagrant-scp?expand=1&linkrev=base&rev=eb31bb09da66845da76334c0554d062f",
        "body": "",
        "status": 200,
        "response": "<directory name=\"vagrant-scp\" rev=\"eb31bb09da66845da76334c0554d062f\" srcmd5=\"eb31bb09da66845da76334c0554d062f\">\n  <entry name=\"vagrant-scp-0.5.7.gem\" md5=\"5f5783c9015a346dc703f6b3a0a360bb\" size=\"7680\" mtime=\"1559805476\"/>\n  <entry name=\"vagrant-scp.changes\" md5=\"1b58a226c28184b72c2b00c1f422e42f\" size=\"189\" mtime=\"1559805476\"/>\n  <entry name=\"vagrant-scp.spec\" md5=\"901e6fc783baab282051a5c2d33c8bfc\" size=\"2481\" mtime=\"1559925765\"/>\n</directory>\n",
        "rawHeaders": [
            "Date",
            "Fri, 29 May 2020 10:22:04 GMT",
            "Server",
            "Apache/2.4.33 (Linux/SUSE)",
            "Strict-Transport-Security",
            "max-age=31536000",
            "cache-control",
            "private, no-transform",
            "referrer-policy",
            "strict-origin-when-cross-origin",
            "x-permitted-cross-domain-policies",
            "none",
            "x-xss-protection",
            "1; mode=block",
            "x-opensuse-runtimes",
            "{\"view\":null,\"db\":13.124007266014814,\"backend\":0}",
            "x-request-id",
            "01dbd9e8-594e-4448-9541-552c786feabb",
            "x-opensuse-apiversion",
            "2.11~alpha.20200525T144748.3dca262e02",
            "x-download-options",
            "noopen",
            "x-runtime",
            "0.039906",
            "x-frame-options",
            "SAMEORIGIN",
            "x-content-type-options",
            "nosniff",
            "x-powered-by",
            "Phusion Passenger 6.0.4",
            "content-type",
            "text/xml",
            "cache-control",
            "no-cache",
            "content-length",
            "447",
            "Connection",
            "close"
        ],
        "responseIsBinary": false
    },
    {
        "scope": "https://api.opensuse.org:443",
        "method": "GET",
        "path": "/source/Virtualization:vagrant/vagrant-scp?expand=1&linkrev=base&rev=3e0e3566753dca94980d3acd23b82efd",
        "body": "",
        "status": 200,
        "response": "<directory name=\"vagrant-scp\" rev=\"3e0e3566753dca94980d3acd23b82efd\" srcmd5=\"3e0e3566753dca94980d3acd23b82efd\">\n  <entry name=\"0001-change-dependency-on-bundler-to-2.1.patch\" md5=\"8d191aba887b640115e1f133e57d856d\" size=\"855\" mtime=\"1585132168\"/>\n  <entry name=\"0002-change-dependency-on-net-scp-to-2.0.patch\" md5=\"59567f9e2785cd89678a580b9a05f510\" size=\"756\" mtime=\"1585132168\"/>\n  <entry name=\"vagrant-scp-0.5.7.gem\" md5=\"5f5783c9015a346dc703f6b3a0a360bb\" size=\"7680\" mtime=\"1559805476\"/>\n  <entry name=\"vagrant-scp.changes\" md5=\"f1bde4de093da6d0a7d363c8ab386d97\" size=\"917\" mtime=\"1585132169\"/>\n  <entry name=\"vagrant-scp.spec\" md5=\"6401a0459cc9b66146002989b55c96d0\" size=\"2834\" mtime=\"1585132170\"/>\n</directory>\n",
        "rawHeaders": [
            "Date",
            "Fri, 29 May 2020 10:22:04 GMT",
            "Server",
            "Apache/2.4.33 (Linux/SUSE)",
            "Strict-Transport-Security",
            "max-age=31536000",
            "cache-control",
            "private, no-transform",
            "referrer-policy",
            "strict-origin-when-cross-origin",
            "x-permitted-cross-domain-policies",
            "none",
            "x-xss-protection",
            "1; mode=block",
            "x-opensuse-runtimes",
            "{\"view\":null,\"db\":13.747514225542545,\"backend\":0}",
            "x-request-id",
            "fa061203-9850-445a-a785-5f0e5d67d07d",
            "x-opensuse-apiversion",
            "2.11~alpha.20200525T144748.3dca262e02",
            "x-download-options",
            "noopen",
            "x-runtime",
            "0.038250",
            "x-frame-options",
            "SAMEORIGIN",
            "x-content-type-options",
            "nosniff",
            "x-powered-by",
            "Phusion Passenger 6.0.4",
            "content-type",
            "text/xml",
            "cache-control",
            "no-cache",
            "content-length",
            "715",
            "Connection",
            "close"
        ],
        "responseIsBinary": false
    },
    {
        "scope": "https://api.opensuse.org:443",
        "method": "GET",
        "path": "/source/Virtualization:vagrant/vagrant-scp?expand=1&linkrev=base&rev=7303deb8640d5adce5b8f09c9638fbaf",
        "body": "",
        "status": 200,
        "response": "<directory name=\"vagrant-scp\" rev=\"7303deb8640d5adce5b8f09c9638fbaf\" srcmd5=\"7303deb8640d5adce5b8f09c9638fbaf\">\n  <entry name=\"0001-change-dependency-on-bundler-to-2.0.patch\" md5=\"a451409b3ee0893ba41d34927d2674c4\" size=\"969\" mtime=\"1561666080\"/>\n  <entry name=\"0002-change-dependency-on-net-scp-to-2.0.patch\" md5=\"bf26d9e9ee2e07a7146aac3bc727b1db\" size=\"870\" mtime=\"1561666080\"/>\n  <entry name=\"vagrant-scp-0.5.7.gem\" md5=\"5f5783c9015a346dc703f6b3a0a360bb\" size=\"7680\" mtime=\"1559805476\"/>\n  <entry name=\"vagrant-scp.changes\" md5=\"5ff2b463dadc41cb5b8ec836aeb021c0\" size=\"567\" mtime=\"1561666080\"/>\n  <entry name=\"vagrant-scp.spec\" md5=\"9955049dd2e692520720de9dfe6b4514\" size=\"2847\" mtime=\"1561666081\"/>\n</directory>\n",
        "rawHeaders": [
            "Date",
            "Fri, 29 May 2020 10:22:04 GMT",
            "Server",
            "Apache/2.4.33 (Linux/SUSE)",
            "Strict-Transport-Security",
            "max-age=31536000",
            "cache-control",
            "private, no-transform",
            "referrer-policy",
            "strict-origin-when-cross-origin",
            "x-permitted-cross-domain-policies",
            "none",
            "x-xss-protection",
            "1; mode=block",
            "x-opensuse-runtimes",
            "{\"view\":null,\"db\":15.417187009006739,\"backend\":0}",
            "x-request-id",
            "e8ebaa21-dfb7-4fca-aa31-8d2976598ed3",
            "x-opensuse-apiversion",
            "2.11~alpha.20200525T144748.3dca262e02",
            "x-download-options",
            "noopen",
            "x-runtime",
            "0.044195",
            "x-frame-options",
            "SAMEORIGIN",
            "x-content-type-options",
            "nosniff",
            "x-powered-by",
            "Phusion Passenger 6.0.4",
            "content-type",
            "text/xml",
            "cache-control",
            "no-cache",
            "content-length",
            "715",
            "Connection",
            "close"
        ],
        "responseIsBinary": false
    },
    {
        "scope": "https://api.opensuse.org:443",
        "method": "GET",
        "path": "/source/Virtualization:vagrant/vagrant-scp?expand=1&linkrev=base&rev=5bc0dc1d511915859525852bc11eee1d",
        "body": "",
        "status": 200,
        "response": "<directory name=\"vagrant-scp\" rev=\"5bc0dc1d511915859525852bc11eee1d\" srcmd5=\"5bc0dc1d511915859525852bc11eee1d\">\n  <entry name=\"vagrant-scp-0.5.7.gem\" md5=\"5f5783c9015a346dc703f6b3a0a360bb\" size=\"7680\" mtime=\"1559805476\"/>\n  <entry name=\"vagrant-scp.changes\" md5=\"1b58a226c28184b72c2b00c1f422e42f\" size=\"189\" mtime=\"1559805476\"/>\n  <entry name=\"vagrant-scp.spec\" md5=\"a5f3bab21510dfc40b04dd13e7fd369b\" size=\"2317\" mtime=\"1559805476\"/>\n</directory>\n",
        "rawHeaders": [
            "Date",
            "Fri, 29 May 2020 10:22:04 GMT",
            "Server",
            "Apache/2.4.33 (Linux/SUSE)",
            "Strict-Transport-Security",
            "max-age=31536000",
            "cache-control",
            "private, no-transform",
            "referrer-policy",
            "strict-origin-when-cross-origin",
            "x-permitted-cross-domain-policies",
            "none",
            "x-xss-protection",
            "1; mode=block",
            "x-opensuse-runtimes",
            "{\"view\":null,\"db\":18.084148410707712,\"backend\":0}",
            "x-request-id",
            "47352b4b-1f68-4d7b-bc21-d8b026fbb105",
            "x-opensuse-apiversion",
            "2.11~alpha.20200525T144748.3dca262e02",
            "x-download-options",
            "noopen",
            "x-runtime",
            "0.061045",
            "x-frame-options",
            "SAMEORIGIN",
            "x-content-type-options",
            "nosniff",
            "x-powered-by",
            "Phusion Passenger 6.0.4",
            "content-type",
            "text/xml",
            "cache-control",
            "no-cache",
            "content-length",
            "447",
            "Connection",
            "close"
        ],
        "responseIsBinary": false
    }
]